gansdojo/__init__.py
gansdojo/config.py
gansdojo/dojo.py
gansdojo/observable.py
gansdojo/modules/__init__.py
gansdojo/modules/checkpoint.py
gansdojo/modules/console_update.py
gansdojo/modules/run_sample.py
gansdojo/modules/tensorboard.py
test/modules/__init__.py
test/modules/checkpoint_saver_test.py
test/modules/console_updator_test.py
test/modules/mock.py
test/modules/run_sample_test.py
test/modules/tensorboard_test.py
gansdojo-0.1.1.dist-info/LICENSE
gansdojo-0.1.1.dist-info/METADATA
gansdojo-0.1.1.dist-info/WHEEL
gansdojo-0.1.1.dist-info/top_level.txt
gansdojo-0.1.1.dist-info/RECORD
