Metadata-Version: 2.1
Name: gansdojo
Version: 0.1.1
Summary: Simple framework for training Generative Adversarial Networks.
Home-page: https://github.com/nova-zl504/gansdojo
Author: Oliver
Author-email: elvewyn@gmail.com
License: MIT
Platform: UNKNOWN
Requires-Dist: tensorflow (>=1.12)
Requires-Dist: numpy (>=1.9.1)
